<T3DataStructure>
	<sheets>
		<sDEF>
			<ROOT>
				<sheetTitle>LLL:EXT:openweatherapi/Resources/Private/Language/locallang.xlf:flexform.settings.title</sheetTitle>
				<type>array</type>
				<el>
					<settings.projectName>
						<label>LLL:EXT:openweatherapi/Resources/Private/Language/locallang.xlf:flexform.settings.projectName</label>
						<config>
							<type>input</type>
							<size>32</size>
							<max>32</max>
							<eval>trim,alpha,lower</eval>
							<required>true</required>
						</config>
					</settings.projectName>
					<settings.apiKey>
						<label>LLL:EXT:openweatherapi/Resources/Private/Language/locallang.xlf:flexform.settings.apiKey</label>
						<config>
							<type>input</type>
							<size>32</size>
							<max>32</max>
							<eval>trim,alphanum,lower</eval>
							<required>true</required>
						</config>						
					</settings.apiKey>
					<settings.cityCode>
						<label>LLL:EXT:openweatherapi/Resources/Private/Language/locallang.xml:flexform.settings.cityCode</label>
						<config>
							<type>input</type>
							<size>12</size>
							<max>12</max>
							<eval>trim,alphanum</eval>
							<required>true</required>
						</config>						
					</settings.cityCode>						
				</el>
			</ROOT>
		</sDEF>
	</sheets>
</T3DataStructure>